[
  {
    "username": "noor",
    "phone": "0599999999",
    "password": "noor123",
    "email": "noor@example.com",
    "location": "نابلس",
    "bills": [
      { "month": "يونيو 2025", "amount": "90 شيكل", "status": "مدفوعة" },
      { "month": "مايو 2025", "amount": "90 شيكل", "status": "غير مدفوعة" }
    ]
  },
  {
    "username": "mohammed",
    "phone": "0566666666",
    "password": "m123456",
    "email": "mohammed@example.com",
    "location": "رام الله",
    "bills": [
      { "month": "يونيو 2025", "amount": "120 شيكل", "status": "غير مدفوعة" },
      { "month": "مايو 2025", "amount": "120 شيكل", "status": "مدفوعة" }
    ]
  },
  {
    "username": "admin",
    "phone": "0500000000",
    "password": "123",
    "email": "admin@speedx.ps",
    "location": "القدس"
  }
]
